smsapi/__init__.py
smsapi/__version__.py
smsapi/client.py
smsapi/error.py
smsapi/models/__init__.py
smsapi/models/bases.py
smsapi/models/instagram_user.py
smsapi/models/instagram_video.py
smsapi/models/tiktok_user.py
smsapi/models/tiktok_video.py
smsapi/resources/__init__.py
smsapi/resources/base.py
smsapi/resources/instagram.py
smsapi/resources/tiktok.py
bviral_sms_sdk-0.0.3.dist-info/LICENSE
bviral_sms_sdk-0.0.3.dist-info/METADATA
bviral_sms_sdk-0.0.3.dist-info/WHEEL
bviral_sms_sdk-0.0.3.dist-info/top_level.txt
bviral_sms_sdk-0.0.3.dist-info/RECORD
