Metadata-Version: 2.1
Name: bviral-sms-sdk
Version: 0.0.3
Summary: A Python wrapper around for Social Media Data API.
Author: Cherif Mohamed Yassine
Author-email: senpaireymes@gmail.com
License: MIT
Keywords: sms-api,sms-sdk
Classifier: License :: OSI Approved :: Apache Software License
Classifier: Programming Language :: Python
Classifier: Programming Language :: Python :: 3.8
Classifier: Programming Language :: Python :: 3.9
Classifier: Programming Language :: Python :: 3.10
Classifier: Programming Language :: Python :: 3.11
Classifier: Programming Language :: Python :: 3.12
Classifier: Programming Language :: Python :: Implementation :: CPython
Classifier: Programming Language :: Python :: Implementation :: PyPy
Classifier: Topic :: Software Development :: Libraries :: Python Modules
Classifier: Intended Audience :: Developers
License-File: LICENSE
Requires-Dist: pydantic >=2.4.2
Requires-Dist: requests >=2.24.0
Requires-Dist: dataclasses-json >=0.6.0
